scrapy_cabinet/__init__.py
scrapy_cabinet/__version__.py
scrapy_cabinet/constants.py
scrapy_cabinet/exceptions.py
scrapy_cabinet/types.py
scrapy_cabinet/utils.py
scrapy_cabinet/downloadermiddlewares/__init__.py
scrapy_cabinet/downloadermiddlewares/proxy_downloader_middleware.py
scrapy_cabinet/extensions/__init__.py
scrapy_cabinet/extensions/redis_spider_idle_closed_extensions.py
scrapy_cabinet/items/__init__.py
scrapy_cabinet/libs/__init__.py
scrapy_cabinet/libs/defaults.py
scrapy_cabinet/libs/utils.py
scrapy_cabinet/libs/gne/__init__.py
scrapy_cabinet/libs/gne/extractor/AuthorExtractor.py
scrapy_cabinet/libs/gne/extractor/ContentExtractor.py
scrapy_cabinet/libs/gne/extractor/TimeExtractor.py
scrapy_cabinet/libs/gne/extractor/TitleExtractor.py
scrapy_cabinet/libs/gne/extractor/__init__.py
scrapy_cabinet/libs/sle/__init__.py
scrapy_cabinet/libs/sle/extractor/ListExtractor.py
scrapy_cabinet/libs/sle/extractor/TimeExtractor.py
scrapy_cabinet/libs/sle/extractor/TitleExtractor.py
scrapy_cabinet/libs/sle/extractor/URLExtractor.py
scrapy_cabinet/libs/sle/extractor/__init__.py
scrapy_cabinet/spidermiddlewares/__init__.py
scrapy_cabinet/spidermiddlewares/extract_spider_middleware.py
scrapy_cabinet/spiders/__init__.py
scrapy_cabinet/spiders/cabinet_spider.py
scrapy_cabinet-0.0.4.dist-info/LICENSE
scrapy_cabinet-0.0.4.dist-info/METADATA
scrapy_cabinet-0.0.4.dist-info/WHEEL
scrapy_cabinet-0.0.4.dist-info/top_level.txt
scrapy_cabinet-0.0.4.dist-info/RECORD
