Metadata-Version: 2.1
Name: scrapy-cabinet
Version: 0.0.4
Summary: Middlewares and Extenstions for Scrapy and ScrapyRedis
Home-page: http://gitlab.nuist.pro:3000/aberstone/scrapy_cabinet.git
Author: Aberstone
Author-email: aberstone.hk@gmail.com
License: MIT License
Platform: UNKNOWN
Classifier: Development Status :: 5 - Production/Stable
Classifier: Intended Audience :: Developers
Classifier: Natural Language :: English
Classifier: License :: OSI Approved :: MIT License
Classifier: Programming Language :: Python
Classifier: Programming Language :: Python :: 2
Classifier: Programming Language :: Python :: 2.7
Classifier: Programming Language :: Python :: 3
Classifier: Programming Language :: Python :: 3.5
Classifier: Programming Language :: Python :: 3.6
Classifier: Programming Language :: Python :: 3.7
Classifier: Programming Language :: Python :: 3.8
Classifier: Programming Language :: Python :: Implementation :: CPython
Classifier: Programming Language :: Python :: Implementation :: PyPy
Requires-Python: >=2.7, !=3.0.*, !=3.1.*, !=3.2.*, !=3.3.*, !=3.4.*
Requires-Dist: Scrapy (==1.8.0)
Requires-Dist: jsonpath (==0.82)
Requires-Dist: loguru (==0.3.2)
Requires-Dist: lxml (==4.4.1)
Requires-Dist: numpy (==1.17.3)
Requires-Dist: scrapy-redis (==0.6.8)
Requires-Dist: setuptools (==41.6.0)
